ApplicationLibrary/DesktopLibrary.py
ApplicationLibrary/MobileLibrary.py
ApplicationLibrary/__init__.py
ApplicationLibrary/Helpers/AppiumCommon.py
ApplicationLibrary/Helpers/__init__.py
robotframework_applicationlibrary-1.2.1.dist-info/LICENSE
robotframework_applicationlibrary-1.2.1.dist-info/METADATA
robotframework_applicationlibrary-1.2.1.dist-info/WHEEL
robotframework_applicationlibrary-1.2.1.dist-info/top_level.txt
robotframework_applicationlibrary-1.2.1.dist-info/RECORD
