Metadata-Version: 2.1
Name: robotframework-applicationlibrary
Version: 1.2.1
Summary: Robot Framework framework for mobile and desktop testing.
Home-page: https://github.com/Accruent/robotframework-applicationlibrary
Maintainer: Brandon Wolfe, Neil Howell, Matt Bozek, Pinky Majhi
Maintainer-email: robosquad@accruent.com
License: GPL-3.0
Keywords: Robot Framework robot-framework selenium appium winappdriver appium robotframeworkdesktop windows zoomba python robotframework-library appium-windows appiumlibraryappium-mobile mobile applicationlibrary application app lib
Platform: any
Classifier: Development Status :: 5 - Production/Stable
Classifier: Operating System :: OS Independent
Classifier: Programming Language :: Python :: 3
Classifier: Topic :: Software Development :: Testing
Classifier: Framework :: Robot Framework :: Library
License-File: LICENSE
Requires-Dist: robotframework (>=5.0)
Requires-Dist: selenium (==3.141.0)
Requires-Dist: robotframework-appiumlibrary (==1.6.4)
Requires-Dist: psutil (>=5.6.0)
Requires-Dist: Appium-Python-Client (==1.3.0)
Requires-Dist: urllib3 (<=1.26.16)
Provides-Extra: testing
Requires-Dist: Appium-Python-Client ; extra == 'testing'
Requires-Dist: mock ; extra == 'testing'
